nonebot_plugin_gocqhttp/__init__.py
nonebot_plugin_gocqhttp/exceptions.py
nonebot_plugin_gocqhttp/external_proxy.py
nonebot_plugin_gocqhttp/log.py
nonebot_plugin_gocqhttp/plugin.py
nonebot_plugin_gocqhttp/plugin_config.py
nonebot_plugin_gocqhttp/process/__init__.py
nonebot_plugin_gocqhttp/process/config-template.yml
nonebot_plugin_gocqhttp/process/config.py
nonebot_plugin_gocqhttp/process/device/__init__.py
nonebot_plugin_gocqhttp/process/device/android_builds.csv
nonebot_plugin_gocqhttp/process/device/android_devices.csv
nonebot_plugin_gocqhttp/process/device/data_source.py
nonebot_plugin_gocqhttp/process/device/generator.py
nonebot_plugin_gocqhttp/process/device/models.py
nonebot_plugin_gocqhttp/process/download.py
nonebot_plugin_gocqhttp/process/manager.py
nonebot_plugin_gocqhttp/process/models.py
nonebot_plugin_gocqhttp/process/platform.py
nonebot_plugin_gocqhttp/process/process.py
nonebot_plugin_gocqhttp/web/.gitignore
nonebot_plugin_gocqhttp/web/__init__.py
nonebot_plugin_gocqhttp/web/api.py
nonebot_plugin_gocqhttp/web/dist/css/290.7fbd3c05.css
nonebot_plugin_gocqhttp/web/dist/css/477.e40964b0.css
nonebot_plugin_gocqhttp/web/dist/css/666.d23b86f9.css
nonebot_plugin_gocqhttp/web/dist/css/679.e40964b0.css
nonebot_plugin_gocqhttp/web/dist/css/app.bd26fad1.css
nonebot_plugin_gocqhttp/web/dist/editor.worker.afbd84bf87ff32f64c63d43e1a5dde9a.js
nonebot_plugin_gocqhttp/web/dist/favicon.ico
nonebot_plugin_gocqhttp/web/dist/fonts/KFOkCnqEu92Fr1MmgVxIIzQ.68bb21d0.woff
nonebot_plugin_gocqhttp/web/dist/fonts/KFOlCnqEu92Fr1MmEU9fBBc-.48af7707.woff
nonebot_plugin_gocqhttp/web/dist/fonts/KFOlCnqEu92Fr1MmSU5fBBc-.c2f7ab22.woff
nonebot_plugin_gocqhttp/web/dist/fonts/KFOlCnqEu92Fr1MmWUlfBBc-.77ecb942.woff
nonebot_plugin_gocqhttp/web/dist/fonts/KFOlCnqEu92Fr1MmYUtfBBc-.f5677eb2.woff
nonebot_plugin_gocqhttp/web/dist/fonts/KFOmCnqEu92Fr1Mu4mxM.f1e2a767.woff
nonebot_plugin_gocqhttp/web/dist/fonts/codicon.4a477f66.ttf
nonebot_plugin_gocqhttp-0.6.12.dist-info/LICENSE
nonebot_plugin_gocqhttp-0.6.12.dist-info/METADATA
nonebot_plugin_gocqhttp-0.6.12.dist-info/WHEEL
nonebot_plugin_gocqhttp-0.6.12.dist-info/RECORD
