Metadata-Version: 2.1
Name: nonebot-plugin-gocqhttp
Version: 0.6.12
Summary: A plugin to run go-cqhttp directly in NoneBot2, without additional download and installation.
Home-page: https://github.com/mnixry/nonebot-plugin-gocqhttp
License: AGPL-3.0
Author: Mix
Author-email: mnixry@users.noreply.github.com
Requires-Python: >=3.8,<4.0
Classifier: License :: OSI Approved :: GNU Affero General Public License v3
Classifier: Programming Language :: Python :: 3
Classifier: Programming Language :: Python :: 3.8
Classifier: Programming Language :: Python :: 3.9
Classifier: Programming Language :: Python :: 3.10
Classifier: Programming Language :: Python :: 3.11
Provides-Extra: proxy
Requires-Dist: chevron (>=0.14.0,<0.15.0)
Requires-Dist: httpx (>=0.20.0)
Requires-Dist: nonebot-adapter-onebot (>=2.0.0,<3.0.0)
Requires-Dist: nonebot2[fastapi] (>=2.0.0,<3.0.0)
Requires-Dist: proxy.py (>=2.4.3,<3.0.0) ; extra == "proxy"
Requires-Dist: psutil (>=5.9.0,<6.0.0)
Requires-Dist: py-cpuinfo (>=8,<10)
Project-URL: Repository, https://github.com/mnixry/nonebot-plugin-gocqhttp
